LICENSE
MANIFEST.in
README.md
setup.py
src/wheezy/__init__.py
src/wheezy.routing.egg-info/PKG-INFO
src/wheezy.routing.egg-info/SOURCES.txt
src/wheezy.routing.egg-info/dependency_links.txt
src/wheezy.routing.egg-info/namespace_packages.txt
src/wheezy.routing.egg-info/not-zip-safe
src/wheezy.routing.egg-info/top_level.txt
src/wheezy/routing/__init__.py
src/wheezy/routing/builders.py
src/wheezy/routing/choice.py
src/wheezy/routing/config.py
src/wheezy/routing/curly.py
src/wheezy/routing/plain.py
src/wheezy/routing/regex.py
src/wheezy/routing/route.py
src/wheezy/routing/router.py
src/wheezy/routing/utils.py